carryon.py
CarryOn-0.1.3.dist-info/METADATA
CarryOn-0.1.3.dist-info/WHEEL
CarryOn-0.1.3.dist-info/entry_points.txt
CarryOn-0.1.3.dist-info/top_level.txt
CarryOn-0.1.3.dist-info/RECORD
