Metadata-Version: 2.1
Name: CarryOn
Version: 0.1.3
Summary: Pack your Python script with its dependencies
Author-email: Oren Tirosh <orent@hishome.net>
License: MIT License
Classifier: Development Status :: 4 - Beta
Classifier: Environment :: Console
Classifier: Intended Audience :: Developers
Classifier: License :: OSI Approved :: MIT License
Classifier: Programming Language :: Python :: 3
Classifier: Topic :: Software Development :: Build Tools
Requires-Python: >=3.6
